advancedEXASOL/__init__.py
advancedEXASOL/advanced_exasol.py
advancedEXASOL/decorator.py
advancedEXASOL-0.2.0.dist-info/LICENSE
advancedEXASOL-0.2.0.dist-info/METADATA
advancedEXASOL-0.2.0.dist-info/WHEEL
advancedEXASOL-0.2.0.dist-info/top_level.txt
advancedEXASOL-0.2.0.dist-info/RECORD
