Metadata-Version: 2.1
Name: advancedEXASOL
Version: 0.2.0
Summary: advancedEXASOL is a Python library that extends pyexasol's functionality.
Home-page: https://github.com/DamienDrash/advancedEXASOL
Author: Damien Frigewski
Author-email: Damien Frigewski <dfrigewski@gmail.com>
License: MIT
Project-URL: Homepage, https://github.com/DamienDrash/advancedEXASOL
Project-URL: Bug Tracker, https://github.com/DamienDrash/advancedEXASOL/issues
Classifier: Programming Language :: Python :: 3
Classifier: License :: OSI Approved :: MIT License
Classifier: Operating System :: OS Independent
Requires-Python: >=3.6
License-File: LICENSE
Requires-Dist: pyexasol
Requires-Dist: dask
Requires-Dist: pandas
Requires-Dist: xlwt
